MANIFEST.in
README.rst
coid.py
setup.py
coid.egg-info/PKG-INFO
coid.egg-info/SOURCES.txt
coid.egg-info/dependency_links.txt
coid.egg-info/requires.txt
coid.egg-info/top_level.txt