Metadata-Version: 1.1
Name: coid
Version: 0.1.0
Summary: Id codecs.
Home-page: https://github.com/bninja/coid
Author: stu
Author-email: stu@unger.rummy
License: BSD
Platform: any
Classifier: Environment :: Web Environment
Classifier: Intended Audience :: Developers
Classifier: License :: OSI Approved :: BSD License
Classifier: Operating System :: OS Independent
Classifier: Programming Language :: Python
Classifier: Topic :: Internet :: WWW/HTTP :: Dynamic Content
Classifier: Topic :: Software Development :: Libraries :: Python Modules
